setup.py
mengheng_probability/Binomialdistribution.py
mengheng_probability/Gaussiandistribution.py
mengheng_probability/Generaldistribution.py
mengheng_probability/__init__.py
mengheng_probability.egg-info/PKG-INFO
mengheng_probability.egg-info/SOURCES.txt
mengheng_probability.egg-info/dependency_links.txt
mengheng_probability.egg-info/not-zip-safe
mengheng_probability.egg-info/top_level.txt