Metadata-Version: 1.0
Name: mengheng-probability
Version: 0.1
Summary: Gaussian and Binomial distributions
Home-page: UNKNOWN
Author: Mengheng Xue
Author-email: mx586@nyu.edu
License: UNKNOWN
Platform: UNKNOWN
